sitemapgen/__init__.py
sitemapgen/__main__.py
sitemapgen/cli.py
sitemapgen/helper.py
sitemapgen-0.9.9.dist-info/LICENSE
sitemapgen-0.9.9.dist-info/METADATA
sitemapgen-0.9.9.dist-info/WHEEL
sitemapgen-0.9.9.dist-info/entry_points.txt
sitemapgen-0.9.9.dist-info/top_level.txt
sitemapgen-0.9.9.dist-info/RECORD
