Metadata-Version: 2.1
Name: sitemapgen
Version: 0.9.9
Summary: A package to generate Sitemaps from a URL. Also provides a CLI for non programmatical use.
Home-page: https://www.nalinangrish.me/apps/sitemapgen
Author: Nalin Angrish
Author-email: nalin@nalinangrish.me
License: UNKNOWN
Platform: UNKNOWN
Classifier: Programming Language :: Python :: 3
Classifier: License :: OSI Approved :: MIT License
Classifier: Operating System :: OS Independent
Requires-Python: >=3.0
Requires-Dist: cloudscraper
Requires-Dist: bs4
